AUTHORS
ChangeLog
LICENSE
README.md
requirements.txt
setup.cfg
setup.py
sayml/__init__.py
sayml.egg-info/PKG-INFO
sayml.egg-info/SOURCES.txt
sayml.egg-info/dependency_links.txt
sayml.egg-info/not-zip-safe
sayml.egg-info/pbr.json
sayml.egg-info/requires.txt
sayml.egg-info/top_level.txt
tests/test_import.py
tests/data/create.yml
tests/data/create_two.yml