Metadata-Version: 1.1
Name: sayml
Version: 1.0.6
Summary: import YAML files into SQLAlchemy
Home-page: https://github.com/adimian/sayml
Author: See AUTHORS
Author-email: eric@adimian.com
License: UNKNOWN
Platform: UNKNOWN
Classifier: Development Status :: 4 - Beta
Classifier: Operating System :: MacOS :: MacOS X
Classifier: Operating System :: Microsoft :: Windows
Classifier: Operating System :: POSIX
Classifier: License :: OSI Approved :: MIT License
Classifier: Programming Language :: Python
Classifier: Programming Language :: Python :: 3.5
